setup.py
dsnd_probability_oa/Binomialdistribution.py
dsnd_probability_oa/Gaussiandistribution.py
dsnd_probability_oa/Generaldistribution.py
dsnd_probability_oa/__init__.py
dsnd_probability_oa.egg-info/PKG-INFO
dsnd_probability_oa.egg-info/SOURCES.txt
dsnd_probability_oa.egg-info/dependency_links.txt
dsnd_probability_oa.egg-info/not-zip-safe
dsnd_probability_oa.egg-info/top_level.txt